pandas_money/__init__.py
pandas_money/money_dtype.py
pandas_money/tests/__init__.py
pandas_money/tests/test_indexing.py
pandas_money/tests/test_money_dtype.py
pandas_money-1.0.0.dist-info/LICENSE
pandas_money-1.0.0.dist-info/METADATA
pandas_money-1.0.0.dist-info/WHEEL
pandas_money-1.0.0.dist-info/RECORD
