Metadata-Version: 2.1
Name: pandas-money
Version: 1.0.0
Summary: A Pandas ArrayExtension for handling currency with int64 performance
Home-page: https://github.com/rmorison/pandas-money
License: MIT
Author: Rod Morison
Author-email: rmorison@users.noreply.github.com
Requires-Python: >=3.11,<4.0
Classifier: License :: OSI Approved :: MIT License
Classifier: Programming Language :: Python :: 3
Classifier: Programming Language :: Python :: 3.11
Requires-Dist: pandas (>=2.0.2,<3.0.0)
Requires-Dist: pandas-stubs (>=2.0.2.230605,<3.0.0.0)
Requires-Dist: py-moneyed (>=3.0,<4.0)
Project-URL: Repository, https://github.com/rmorison/pandas-money
